{
    "name": "fwd-modules-fwd-rpm",
    "dependencies": {
        "core": "*",
        "radio": "*",
        "microphone": "*",
        "pxt-fwd-modules": "github:forward-education/pxt-fwd-modules"
    },
    "files": [
        "main.blocks",
        "main.ts",
        "README.md"
    ],
    "testFiles": [
        "test.ts"
    ],
    "targetVersions": {
        "target": "7.0.61",
        "targetId": "microbit"
    },
    "supportedTargets": [
        "microbit"
    ],
    "preferredEditor": "blocksprj"
}
